ascat/__init__.py
ascat/accessors.py
ascat/cell.py
ascat/cf_array.py
ascat/cgls.py
ascat/file_handling.py
ascat/h_saf.py
ascat/ragged_array.py
ascat/swath.py
ascat/utils.py
ascat/aggregate/__init__.py
ascat/aggregate/aggregators.py
ascat/aggregate/interface.py
ascat/download/connectors.py
ascat/download/interface.py
ascat/eumetsat/__init__.py
ascat/eumetsat/level1.py
ascat/eumetsat/level2.py
ascat/grids/__init__.py
ascat/grids/grid_registry.py
ascat/product_info/__init__.py
ascat/product_info/product_info.py
ascat/read_native/__init__.py
ascat/read_native/base.py
ascat/read_native/bufr.py
ascat/read_native/cdr.py
ascat/read_native/eps_native.py
ascat/read_native/generate_test_data.py
ascat/read_native/hdf5.py
ascat/read_native/nc.py
ascat/read_native/ragged_array_ts.py
ascat/read_native/xarray_io.py
ascat/read_native/formats/ccsds.xml
ascat/read_native/formats/eps.dtd
ascat/read_native/formats/eps.xsl
ascat/read_native/formats/eps_ascatl1bszf_13.1.xml
ascat/read_native/formats/eps_ascatl1bszf_6.4.xml
ascat/read_native/formats/eps_ascatl1bszf_6.4m.xml
ascat/read_native/formats/eps_ascatl1bszf_6.5.xml
ascat/read_native/formats/eps_ascatl1bszf_6.6.xml
ascat/read_native/formats/eps_ascatl1bszf_7.0.xml
ascat/read_native/formats/eps_ascatl1bszf_9.0.xml
ascat/read_native/formats/eps_ascatl1bszo_13.1.xml
ascat/read_native/formats/eps_ascatl1bszo_6.4.xml
ascat/read_native/formats/eps_ascatl1bszo_6.4m.xml
ascat/read_native/formats/eps_ascatl1bszo_6.5.xml
ascat/read_native/formats/eps_ascatl1bszo_6.6.xml
ascat/read_native/formats/eps_ascatl1bszo_7.0.xml
ascat/read_native/formats/eps_ascatl1bszo_9.0.xml
ascat/read_native/formats/eps_ascatl1bszr_13.1.xml
ascat/read_native/formats/eps_ascatl1bszr_6.4.xml
ascat/read_native/formats/eps_ascatl1bszr_6.4m.xml
ascat/read_native/formats/eps_ascatl1bszr_6.5.xml
ascat/read_native/formats/eps_ascatl1bszr_6.6.xml
ascat/read_native/formats/eps_ascatl1bszr_7.0.xml
ascat/read_native/formats/eps_ascatl1bszr_9.0.xml
ascat-2.6.4.dist-info/licenses/LICENSE.txt
ascat-2.6.4.dist-info/METADATA
ascat-2.6.4.dist-info/WHEEL
ascat-2.6.4.dist-info/entry_points.txt
ascat-2.6.4.dist-info/top_level.txt
ascat-2.6.4.dist-info/RECORD
