Metadata-Version: 2.4
Name: ascat
Version: 2.6.4
Summary: Read and process backscatter and soil moisture data from the Advanced Scatterometer (ASCAT)
Home-page: https://tuwien.at/mg/geo/rs
Author: TU Wien
Author-email: remote.sensing@geo.tuwien.ac.at
License: MIT
Project-URL: Documentation, https://ascat.readthedocs.org/
Platform: any
Classifier: Development Status :: 4 - Beta
Classifier: Programming Language :: Python
License-File: LICENSE.txt
Requires-Dist: importlib-metadata; python_version < "3.8"
Requires-Dist: numpy
Requires-Dist: pandas
Requires-Dist: netCDF4
Requires-Dist: pykdtree
Requires-Dist: pyresample
Requires-Dist: h5py
Requires-Dist: h5netcdf
Requires-Dist: xarray
Requires-Dist: dask
Requires-Dist: shapely
Requires-Dist: cadati
Requires-Dist: pygeogrids
Requires-Dist: fibgrid
Requires-Dist: tqdm
Requires-Dist: yapf
Requires-Dist: flake8
Requires-Dist: pytest
Requires-Dist: pytest-cov
Requires-Dist: pytest-mpl
Provides-Extra: testing
Requires-Dist: setuptools; extra == "testing"
Requires-Dist: pytest; extra == "testing"
Requires-Dist: pytest-cov; extra == "testing"
Dynamic: license-file
